<?xml version="1.0" encoding="utf-8" ?>
<dwsync>
<file name="jquery.prettyPhoto.js" server="server10.nixiweb.com" local="3437585568" remote="318763443830460612" />
<file name="jquery.ui.autocomplete.js" server="server10.nixiweb.com" local="3437585568" remote="318763443830460612" />
<file name="jquery.ui.position.js" server="server10.nixiweb.com" local="3437585568" remote="318763443830460612" />
<file name="jquery.ui.widget.js" server="server10.nixiweb.com" local="3437585568" remote="318763443830460612" />
<file name="jquery.prettyPhoto.js" server="server1.nixiweb.com" local="3437585568" remote="318763443830615112" />
<file name="jquery.ui.autocomplete.js" server="server1.nixiweb.com" local="3437585568" remote="318763443830615112" />
<file name="jquery.ui.position.js" server="server1.nixiweb.com" local="3437585568" remote="318763443830615172" />
<file name="jquery.ui.widget.js" server="server1.nixiweb.com" local="3437585568" remote="318763443830615172" />
<file name="jquery.ui.position.js" server="estutiempo.xtrweb.com" local="130029212613618230" remote="130060137000000000" />
<file name="jquery.ui.widget.js" server="estutiempo.xtrweb.com" local="130029212613462243" remote="130060137000000000" />
<file name="jquery.ui.autocomplete.js" server="estutiempo.xtrweb.com" local="130029212613306229" remote="130060137000000000" />
<file name="jquery.prettyPhoto.js" server="estutiempo.xtrweb.com" local="130029212613930237" remote="130060137000000000" />
<file name="jquery.ui.position.js" server="31.170.163.174" local="130055752780763362" remote="130058467800000000" />
<file name="jquery.ui.widget.js" server="31.170.163.174" local="130055752780763362" remote="130058467800000000" />
<file name="jquery.ui.autocomplete.js" server="31.170.163.174" local="130055752780607361" remote="130058467800000000" />
<file name="jquery.prettyPhoto.js" server="31.170.163.174" local="130055752780919362" remote="130057427400000000" />
<file name="jquery.scrollTo.min.js" server="31.170.163.174" local="130055752780919362" remote="130058467800000000" />
<file name="jquery.scrollTo.min.js" server="estutiempo.xtrweb.com" local="130029212613150246" remote="130060137000000000" />
<file name="jquery.prettyPhoto.js" server="93.188.160.45" local="130065372625131047" remote="130065286800000000" />
<file name="jquery.scrollTo.min.js" server="93.188.160.45" local="130065372622730910" remote="130065184200000000" />
<file name="jquery.ui.position.js" server="93.188.160.45" local="130065372624471010" remote="130065184200000000" />
<file name="jquery.ui.autocomplete.js" server="93.188.160.45" local="130065372622900920" remote="130065184200000000" />
<file name="jquery.ui.widget.js" server="93.188.160.45" local="130065372624010983" remote="130065184200000000" />
<file name="jquery.prettyPhoto.js" server="93.188.160.42" local="130065372625131047" remote="130065882600000000" />
<file name="jquery.ui.position.js" server="93.188.160.42" local="130065372624471010" remote="130065882600000000" />
<file name="jquery.scrollTo.min.js" server="93.188.160.42" local="130065372622730910" remote="130065882600000000" />
<file name="jquery.ui.autocomplete.js" server="93.188.160.42" local="130065372622900920" remote="130065882600000000" />
<file name="jquery.ui.widget.js" server="93.188.160.42" local="130065372624010983" remote="130065882600000000" />
<file name="jquery.ui.position.js" server="93.188.160.46" local="130071304015498761" remote="130071956400000000" />
<file name="jquery.ui.widget.js" server="93.188.160.46" local="130071304015398760" remote="130071956400000000" />
<file name="jquery.ui.autocomplete.js" server="93.188.160.46" local="130071304015098760" remote="130071956400000000" />
<file name="jquery.scrollTo.min.js" server="93.188.160.46" local="130071304015898761" remote="130071956400000000" />
<file name="jquery.prettyPhoto.js" server="93.188.160.46" local="130071304015598761" remote="130071976800000000" />
<file name="jquery.scrollTo.min.js" server="93.188.160.39" local="130071296175864314" remote="130072058400000000" />
<file name="jquery.ui.autocomplete.js" server="93.188.160.39" local="130071296174044875" remote="130072058400000000" />
<file name="jquery.ui.widget.js" server="93.188.160.39" local="130071296174593332" remote="130072058400000000" />
<file name="jquery.ui.position.js" server="93.188.160.39" local="130071296174787065" remote="130072058400000000" />
<file name="jquery.prettyPhoto.js" server="93.188.160.39" local="130071296175124329" remote="130072059600000000" />
<file name="jquery.prettyPhoto.js" server="93.188.160.13" local="130074995825048608" remote="130074828000000000" />
<file name="jquery.scrollTo.min.js" server="93.188.160.13" local="130074995825198610" remote="130074828000000000" />
<file name="jquery.ui.position.js" server="93.188.160.13" local="130074995824973606" remote="130074828000000000" />
<file name="jquery.ui.widget.js" server="93.188.160.13" local="130074995824898605" remote="130074828000000000" />
<file name="jquery.ui.autocomplete.js" server="93.188.160.13" local="130074995824398598" remote="130074828000000000" />
<file name="jquery.ui.position.js" server="31.170.166.139" local="130076424729917994" remote="130076259600000000" />
<file name="jquery.ui.widget.js" server="31.170.166.139" local="130076424729292984" remote="130076259600000000" />
<file name="jquery.ui.autocomplete.js" server="31.170.166.139" local="130076424728617974" remote="130076259600000000" />
<file name="jquery.scrollTo.min.js" server="31.170.166.139" local="130076424730242999" remote="130076259600000000" />
<file name="jquery.prettyPhoto.js" server="31.170.166.139" local="130076424730155498" remote="130076257800000000" />
<file name="jquery.ui.datepicker-es.js" server="31.170.166.139" local="130076424728542973" remote="130076257800000000" />
</dwsync>